libfunx/README.md
libfunx/__init__.py
libfunx/__main__.py
libfunx-0.9.4.dist-info/WHEEL
libfunx-0.9.4.dist-info/METADATA
libfunx-0.9.4.dist-info/RECORD
